{"generated_at":"2025-12-25T07:23:18.755Z","events_index":[{"id":"evt-001","title":"里山たんけん隊：春の生きもの探し","image":"evt-001.jpg_uqv2y2","city":"世田谷","prefecture":"東京都","price":1500,"isRecommended":true,"isNew":true,"rating":4.5,"reviewCount":0,"categoryId":"","area":"","organizerId":"org-001","organizer_id":"org-001","publishedAt":"","next_date":"2026-02-01","date_min":"2026-02-01","date_max":"2026-02-28"},{"id":"evt-002","title":"焚き火ではじめる火の科学","image":"https://picsum.photos/seed/evt3/800/600","city":"世田谷","prefecture":"東京都","price":2000,"isRecommended":false,"isNew":true,"rating":4.5,"reviewCount":0,"categoryId":"","area":"","organizerId":"org-002","organizer_id":"org-002","publishedAt":"","next_date":"2026-02-02","date_min":"2026-02-02","date_max":"2026-02-02"},{"id":"evt-003","title":"夜の公園ナイトサファリ","image":"https://picsum.photos/seed/evt3/800/600","city":"世田谷","prefecture":"東京都","price":1800,"isRecommended":true,"isNew":false,"rating":4.5,"reviewCount":0,"categoryId":"","area":"","organizerId":"org-001","organizer_id":"org-001","publishedAt":"","next_date":"2026-02-03","date_min":"2026-02-03","date_max":"2026-02-03"},{"id":"evt-004","title":"葉っぱで分類学入門","image":"https://picsum.photos/seed/evt4/800/600","city":"世田谷","prefecture":"東京都","price":1200,"isRecommended":false,"isNew":false,"rating":4.5,"reviewCount":0,"categoryId":"","area":"","organizerId":"org-003","organizer_id":"org-003","publishedAt":"","next_date":"2026-02-04","date_min":"2026-02-04","date_max":"2026-02-04"},{"id":"evt-005","title":"川の水質調査ラボ","image":"https://picsum.photos/seed/evt5/800/600","city":"世田谷","prefecture":"東京都","price":2200,"isRecommended":true,"isNew":false,"rating":4.5,"reviewCount":0,"categoryId":"","area":"","organizerId":"org-002","organizer_id":"org-002","publishedAt":"","next_date":"2026-02-05","date_min":"2026-02-05","date_max":"2026-02-05"},{"id":"evt-006","title":"石ころ博士になろう","image":"https://picsum.photos/seed/evt6/800/600","city":"世田谷","prefecture":"東京都","price":1000,"isRecommended":false,"isNew":true,"rating":4.5,"reviewCount":0,"categoryId":"","area":"","organizerId":"org-003","organizer_id":"org-003","publishedAt":"","next_date":"2026-02-06","date_min":"2026-02-06","date_max":"2026-02-06"},{"id":"evt-007","title":"親子で星空観察","image":"https://picsum.photos/seed/evt7/800/600","city":"世田谷","prefecture":"東京都","price":1800,"isRecommended":true,"isNew":true,"rating":4.5,"reviewCount":0,"categoryId":"","area":"","organizerId":"org-004","organizer_id":"org-004","publishedAt":"","next_date":"2026-02-07","date_min":"2026-02-07","date_max":"2026-02-07"},{"id":"evt-008","title":"昆虫標本づくり","image":"https://picsum.photos/seed/evt8/800/600","city":"世田谷","prefecture":"東京都","price":2500,"isRecommended":false,"isNew":false,"rating":4.5,"reviewCount":0,"categoryId":"","area":"","organizerId":"org-001","organizer_id":"org-001","publishedAt":"","next_date":"2026-02-08","date_min":"2026-02-08","date_max":"2026-02-08"},{"id":"evt-009","title":"竹で作る水鉄砲","image":"https://picsum.photos/seed/evt9/800/600","city":"世田谷","prefecture":"東京都","price":1500,"isRecommended":false,"isNew":false,"rating":4.5,"reviewCount":0,"categoryId":"","area":"","organizerId":"org-002","organizer_id":"org-002","publishedAt":"","next_date":"2026-02-09","date_min":"2026-02-09","date_max":"2026-02-09"},{"id":"evt-010","title":"土の中のミクロ探検","image":"https://picsum.photos/seed/evt10/800/600","city":"世田谷","prefecture":"東京都","price":2000,"isRecommended":true,"isNew":false,"rating":4.5,"reviewCount":0,"categoryId":"","area":"","organizerId":"org-003","organizer_id":"org-003","publishedAt":"","next_date":"2026-02-10","date_min":"2026-02-10","date_max":"2026-02-10"},{"id":"evt-011","title":"風と凧の科学","image":"https://picsum.photos/seed/evt11/800/600","city":"世田谷","prefecture":"東京都","price":1600,"isRecommended":false,"isNew":true,"rating":4.5,"reviewCount":0,"categoryId":"","area":"","organizerId":"org-004","organizer_id":"org-004","publishedAt":"","next_date":"2026-02-11","date_min":"2026-02-11","date_max":"2026-02-11"},{"id":"evt-012","title":"カエルの一生を追う","image":"https://picsum.photos/seed/evt12/800/600","city":"世田谷","prefecture":"東京都","price":1800,"isRecommended":false,"isNew":false,"rating":4.5,"reviewCount":0,"categoryId":"","area":"","organizerId":"org-001","organizer_id":"org-001","publishedAt":"","next_date":"2026-02-12","date_min":"2026-02-12","date_max":"2026-02-12"},{"id":"evt-013","title":"地層を読む","image":"https://picsum.photos/seed/evt13/800/600","city":"世田谷","prefecture":"東京都","price":1900,"isRecommended":true,"isNew":false,"rating":4.5,"reviewCount":0,"categoryId":"","area":"","organizerId":"org-003","organizer_id":"org-003","publishedAt":"","next_date":"2026-02-13","date_min":"2026-02-13","date_max":"2026-02-13"},{"id":"evt-014","title":"落ち葉アート","image":"https://picsum.photos/seed/evt14/800/600","city":"世田谷","prefecture":"東京都","price":1400,"isRecommended":false,"isNew":false,"rating":4.5,"reviewCount":0,"categoryId":"","area":"","organizerId":"org-002","organizer_id":"org-002","publishedAt":"","next_date":"2026-02-14","date_min":"2026-02-14","date_max":"2026-02-14"},{"id":"evt-015","title":"ミミズのひみつ","image":"https://picsum.photos/seed/evt15/800/600","city":"世田谷","prefecture":"東京都","price":1300,"isRecommended":false,"isNew":false,"rating":4.5,"reviewCount":0,"categoryId":"","area":"","organizerId":"org-001","organizer_id":"org-001","publishedAt":"","next_date":"2026-02-15","date_min":"2026-02-15","date_max":"2026-02-15"},{"id":"evt-016","title":"親子で自然写真","image":"https://picsum.photos/seed/evt16/800/600","city":"世田谷","prefecture":"東京都","price":1700,"isRecommended":false,"isNew":true,"rating":4.5,"reviewCount":0,"categoryId":"","area":"","organizerId":"org-004","organizer_id":"org-004","publishedAt":"","next_date":"2026-02-16","date_min":"2026-02-16","date_max":"2026-02-16"},{"id":"evt-017","title":"雨の日の生きもの観察","image":"https://picsum.photos/seed/evt17/800/600","city":"世田谷","prefecture":"東京都","price":1600,"isRecommended":false,"isNew":false,"rating":4.5,"reviewCount":0,"categoryId":"","area":"","organizerId":"org-003","organizer_id":"org-003","publishedAt":"","next_date":"2026-02-17","date_min":"2026-02-17","date_max":"2026-02-17"},{"id":"evt-018","title":"竹林探検と音づくり","image":"https://picsum.photos/seed/evt18/800/600","city":"世田谷","prefecture":"東京都","price":2100,"isRecommended":true,"isNew":false,"rating":4.5,"reviewCount":0,"categoryId":"","area":"","organizerId":"org-002","organizer_id":"org-002","publishedAt":"","next_date":"2026-02-18","date_min":"2026-02-18","date_max":"2026-02-18"},{"id":"evt-019","title":"自然×数学：かたち探し","image":"https://picsum.photos/seed/evt19/800/600","city":"世田谷","prefecture":"東京都","price":1500,"isRecommended":false,"isNew":false,"rating":4.5,"reviewCount":0,"categoryId":"","area":"","organizerId":"org-004","organizer_id":"org-004","publishedAt":"","next_date":"2026-02-19","date_min":"2026-02-19","date_max":"2026-02-19"},{"id":"evt-020","title":"はじめての野鳥観察","image":"https://picsum.photos/seed/evt20/800/600","city":"多摩市","prefecture":"東京都","price":1800,"isRecommended":true,"isNew":true,"rating":4.5,"reviewCount":0,"categoryId":"","area":"","organizerId":"org-001","organizer_id":"org-001","publishedAt":"","next_date":"2026-02-20","date_min":"2026-02-20","date_max":"2026-02-20"}]}